{
  "landingPageImages": [
    "https://i.imgur.com/m28gEEB.png",
    "https://i.imgur.com/4Mx0mzy.png",
    "https://i.imgur.com/6gUtnby.png",
    "https://i.imgur.com/Vpfgw3D.png",
    "https://i.imgur.com/rDdgfrr.png"
  ],
  "ourTeamImages": [
    "https://i.imgur.com/QB4L7nZ.png",
    "https://i.imgur.com/OtEJFE3.png",
    "https://i.imgur.com/pIMoUku.png"
  ],
  "projectsPageImages": [
    "https://i.imgur.com/ByHHvr1.png",
    "https://i.imgur.com/YHkP6Ip.png",
    "https://i.imgur.com/f8xtpg4.png"
  ],
  "accoladesImages": [
    "https://i.imgur.com/gR6XL9i.png",
    "https://i.imgur.com/R44jCu7.png",
    "https://i.imgur.com/PkUSVSD.png"
  ],
  "youtubeVideo": "m_VWOgJYowo"
}
